{"features": [{"geometry": {"coordinates": [-0.8865299999999999, 41.622766], "type": "Point"}, "properties": {"description": "Donde matan a Felix Chico ", "name": "Cementerio Torrero"}, "type": "Feature"}, {"geometry": {"coordinates": [-0.881957, 41.654785], "type": "Point"}, "properties": {"description": "Donde vive felix chico", "name": "Calle Torre Nueva"}, "type": "Feature"}, {"geometry": {"coordinates": [-0.881402, 41.658614], "type": "Point"}, "properties": {"description": " ", "name": "Puente del Ebro"}, "type": "Feature"}, {"geometry": {"coordinates": [1.1152448999999998, 41.070218], "type": "Point"}, "properties": {"description": "Lugar donde viven de joven y vacaciones", "name": "Grand Oasis Park"}, "type": "Feature"}], "type": "FeatureCollection"}